useq/__init__.py
useq/_actions.py
useq/_base_model.py
useq/_channel.py
useq/_grid.py
useq/_hardware_autofocus.py
useq/_iter_sequence.py
useq/_mda_event.py
useq/_mda_sequence.py
useq/_plate.py
useq/_plate_registry.py
useq/_plot.py
useq/_point_visiting.py
useq/_position.py
useq/_time.py
useq/_utils.py
useq/_z.py
useq/py.typed
useq/pycromanager.py
useq/experimental/__init__.py
useq_schema-0.8.0.dist-info/METADATA
useq_schema-0.8.0.dist-info/WHEEL
useq_schema-0.8.0.dist-info/licenses/LICENSE
useq_schema-0.8.0.dist-info/RECORD
