Metadata-Version: 2.4
Name: useq-schema
Version: 0.8.0
Summary: Schema for multi-dimensional microscopy experiments
Project-URL: Source, https://github.com/pymmcore-plus/useq-schema
Project-URL: Tracker, https://github.com/pymmcore-plus/useq-schema/issues
Author-email: Talley Lambert <talley.lambert@gmail.com>, Federico Gasparoli <federico.gasparoli@gmail.com>
License: BSD 3-Clause License
License-File: LICENSE
Keywords: microscopy,schema
Classifier: Development Status :: 4 - Beta
Classifier: Intended Audience :: Developers
Classifier: Intended Audience :: Science/Research
Classifier: License :: OSI Approved :: BSD License
Classifier: Operating System :: OS Independent
Classifier: Programming Language :: Python
Classifier: Programming Language :: Python :: 3 :: Only
Classifier: Programming Language :: Python :: 3.9
Classifier: Programming Language :: Python :: 3.10
Classifier: Programming Language :: Python :: 3.11
Classifier: Programming Language :: Python :: 3.12
Classifier: Programming Language :: Python :: 3.13
Classifier: Topic :: Scientific/Engineering
Classifier: Topic :: Scientific/Engineering :: Image Processing
Classifier: Topic :: Scientific/Engineering :: Medical Science Apps.
Classifier: Topic :: Software Development
Classifier: Topic :: System :: Hardware
Classifier: Typing :: Typed
Requires-Python: >=3.9
Requires-Dist: numpy>=1.25.2
Requires-Dist: numpy>=1.26.0; python_version >= '3.12'
Requires-Dist: numpy>=2.1.0; python_version >= '3.13'
Requires-Dist: pydantic>=2.6
Requires-Dist: shapely>=2.0.7
Requires-Dist: typing-extensions>=4
Provides-Extra: plot
Requires-Dist: matplotlib>=3.7; extra == 'plot'
Provides-Extra: yaml
Requires-Dist: pyyaml>=5.0; extra == 'yaml'
